{
    "lists":[
        {
            "name":"To Do",
            "done":false,
            "tasks":[
                {
                    "name":"Task 1",
                    "done":false
                },
                {
                    "name":"Task 2",
                    "done":true
                }
            ]
        },
        {
            "name":"depnoiefned",
            "done":true,
            "tasks":[
                {
                    "name":"Task",
                    "done":true
                },
                {
                    "name":"Task",
                    "done":true
                }
            ]
        }
    ]
}
